setup.cfg
setup.py
ptpop/AnnounceMessage.py
ptpop/Console.py
ptpop/FollowUpMessage.py
ptpop/Listener.py
ptpop/PtpNeighbor.py
ptpop/PtpPacket.py
ptpop/SyncMessage.py
ptpop/__init__.py
ptpop/__main__.py
ptpop/_version.py
ptpop.egg-info/PKG-INFO
ptpop.egg-info/SOURCES.txt
ptpop.egg-info/dependency_links.txt
ptpop.egg-info/entry_points.txt
ptpop.egg-info/requires.txt
ptpop.egg-info/top_level.txt