Metadata-Version: 1.0
Name: ptpop
Version: 1.1.0
Summary: top for PTP
Home-page: http://github.com/andrewburnheimer/ptpop
Author: Andrew Burnheimer
Author-email: Andrew.Burnheimer@nbcuni.com
License: ASLv2
Platform: UNKNOWN
